flakepipe/__init__.py
flakepipe/connection.py
flakepipe/uploader.py
flakepipe/utils.py
flakepipe-0.1.2.dist-info/licenses/LICENSE
tests/__init__.py
tests/test_connection.py
tests/test_uploader.py
tests/test_utils.py
flakepipe-0.1.2.dist-info/METADATA
flakepipe-0.1.2.dist-info/WHEEL
flakepipe-0.1.2.dist-info/top_level.txt
flakepipe-0.1.2.dist-info/RECORD
