Metadata-Version: 2.4
Name: flakepipe
Version: 0.1.2
Summary: Reusable module for uploading datasets to Snowflake via stage
Home-page: https://github.com/geeone/flakepipe
Author: Sergei Denisenko
Author-email: sergei.denisenko@ieee.org
License: MIT
Project-URL: Documentation, https://github.com/geeone/flakepipe
Project-URL: Source, https://github.com/geeone/flakepipe
Project-URL: Bug Tracker, https://github.com/geeone/flakepipe/issues
Keywords: snowflake upload ETL csv stage data
Classifier: Development Status :: 4 - Beta
Classifier: Intended Audience :: Developers
Classifier: License :: OSI Approved :: MIT License
Classifier: Operating System :: OS Independent
Classifier: Programming Language :: Python :: 3
Classifier: Programming Language :: Python :: 3 :: Only
Classifier: Programming Language :: Python :: 3.8
Classifier: Programming Language :: Python :: 3.9
Classifier: Programming Language :: Python :: 3.10
Classifier: Programming Language :: Python :: 3.11
Classifier: Topic :: Software Development :: Build Tools
Classifier: Topic :: Software Development :: Libraries :: Python Modules
Classifier: Topic :: Utilities
Requires-Python: >=3.8,<3.12
License-File: LICENSE
Requires-Dist: SQLAlchemy>=1.4.15
Requires-Dist: snowflake-connector-python>=2.8.1
Requires-Dist: snowflake-sqlalchemy>=1.2.4
Requires-Dist: pandas<2.1,>=1.4.0
Requires-Dist: numpy<1.26.0,>=1.21.0
Dynamic: author
Dynamic: author-email
Dynamic: classifier
Dynamic: description
Dynamic: description-content-type
Dynamic: home-page
Dynamic: keywords
Dynamic: license
Dynamic: license-file
Dynamic: project-url
Dynamic: requires-dist
Dynamic: requires-python
Dynamic: summary
